dataweb/__init__.py
dataweb/classdataweb.py
dataweb/mergedataweb.py
dataweb/requestweb/__init__.py
dataweb/threadingtasks/__init__.py
dataweb-0.5.4.dist-info/DESCRIPTION.rst
dataweb-0.5.4.dist-info/METADATA
dataweb-0.5.4.dist-info/RECORD
dataweb-0.5.4.dist-info/WHEEL
dataweb-0.5.4.dist-info/metadata.json
dataweb-0.5.4.dist-info/top_level.txt
