Metadata-Version: 2.0
Name: dataweb
Version: 0.5.4
Summary: Gestión de datos recogidos en web de forma periódica
Home-page: https://github.com/azogue/dataweb
Author: Eugenio Panadero
Author-email: azogue.lab@gmail.com
License: MIT
Keywords: web scraper
Platform: UNKNOWN
Requires-Dist: numpy
Requires-Dist: pandas
Requires-Dist: pytz
Requires-Dist: requests
